{
  "title": "AI 周报 07/02-07/02",
  "summary": "本周 AI 新闻摘要（自动生成失败，请查看下方新闻列表）",
  "highlights": [
    "msitarzewski /agency-agents",
    "usestrix /strix",
    "HKUDS /Vibe-Trading",
    "hasaneyldrm /exercises-dataset",
    "facebook /astryx"
  ],
  "updated": "2026-07-02T10:49:13Z",
  "top_ids": [
    "5dfe15d5980d",
    "11576ef07d08",
    "3888eecb3f45",
    "ac45b546f1b9",
    "af5e1c06972b",
    "10942d97d561",
    "7dc28f2cebb2",
    "1f1729780c9b",
    "27ed64f7c2ff",
    "7786979f533d"
  ]
}